roslibpy/__init__.py
roslibpy/__main__.py
roslibpy/__version__.py
roslibpy/actionlib.py
roslibpy/core.py
roslibpy/event_emitter.py
roslibpy/ros.py
roslibpy/tf.py
roslibpy/comm/__init__.py
roslibpy/comm/comm.py
roslibpy/comm/comm_autobahn.py
roslibpy/comm/comm_cli.py
roslibpy/ros2/__init__.py
roslibpy-1.7.0.dist-info/AUTHORS.rst
roslibpy-1.7.0.dist-info/LICENSE
roslibpy-1.7.0.dist-info/METADATA
roslibpy-1.7.0.dist-info/WHEEL
roslibpy-1.7.0.dist-info/entry_points.txt
roslibpy-1.7.0.dist-info/top_level.txt
roslibpy-1.7.0.dist-info/RECORD
