Metadata-Version: 1.1
Name: roslibpy
Version: 1.7.0
Summary: Python ROS Bridge library.
Home-page: https://github.com/gramaziokohler/roslibpy
Author: Gramazio Kohler Research
Author-email: gramaziokohler@arch.ethz.ch
License: MIT license
Keywords: ros,ros-bridge,robotics,websockets
Platform: UNKNOWN
Classifier: Development Status :: 4 - Beta
Classifier: Intended Audience :: Developers
Classifier: Intended Audience :: Science/Research
Classifier: License :: OSI Approved :: MIT License
Classifier: Operating System :: Unix
Classifier: Operating System :: POSIX
Classifier: Operating System :: Microsoft :: Windows
Classifier: Programming Language :: Python
Classifier: Programming Language :: Python :: 3
Classifier: Programming Language :: Python :: 3.3
Classifier: Programming Language :: Python :: 3.4
Classifier: Programming Language :: Python :: 3.5
Classifier: Programming Language :: Python :: 3.6
Classifier: Programming Language :: Python :: 3.7
Classifier: Programming Language :: Python :: 3.8
Classifier: Programming Language :: Python :: Implementation :: CPython
Classifier: Programming Language :: Python :: Implementation :: IronPython
Classifier: Topic :: Scientific/Engineering
